mlpype/matplotlib/__init__.py
mlpype/matplotlib/evaluate/__init__.py
mlpype/matplotlib/evaluate/matplot.py
mlpype/matplotlib/evaluate/shapley.py
mlpype_matplotlib-0.6.12.dist-info/METADATA
mlpype_matplotlib-0.6.12.dist-info/WHEEL
mlpype_matplotlib-0.6.12.dist-info/RECORD
