Metadata-Version: 2.4
Name: mlpype-matplotlib
Version: 0.6.12
Summary: Matplotlib extension for MLpype
Author: Jeroen van den Hoven
License: MIT
Requires-Python: >=3.9
Requires-Dist: matplotlib>=3.7.5
Requires-Dist: mlpype-base
Requires-Dist: numpy>=1.26.4
Requires-Dist: pandas>=1.5.3
Requires-Dist: shap>=0.46.0
Provides-Extra: strict
Requires-Dist: matplotlib==3.7.5; extra == 'strict'
Requires-Dist: numpy==1.26.4; extra == 'strict'
Requires-Dist: pandas==1.5.3; extra == 'strict'
Requires-Dist: shap==0.46.0; extra == 'strict'
